{
  "Workflows": [
    {
      "Path": null,
      "SortBy": 0,
      "VariablesSectionElementsOrder": [],
      "ArgumentsSectionElementsOrder": null,
      "ConstantsSectionElementsOrder": [],
      "AddedNamespaces": null
    },
    {
      "Path": "Main.xaml",
      "SortBy": 0,
      "VariablesSectionElementsOrder": [
        "INPUT&Sequence_4",
        "dt_Employee&Sequence_1"
      ],
      "ArgumentsSectionElementsOrder": [],
      "ConstantsSectionElementsOrder": [],
      "AddedNamespaces": null
    }
  ]
}